{
    "title": "Amazon EventBridge Scheduler to Amazon EventBridge",
    "description": "Use EventBridge Scheduler to publish an EventBridge event every 5 minutes using templated targets",
    "language": "",
    "level": "300",
    "framework": "Terraform",
    "introBox": {
      "headline": "How it works",
      "text": [
        "This project uses Terraform to create an Schedule that sends custom events to EventBridge that are matched to rules and use CloudWatch as a target to visualize the event pattern matches. The Terraform creates a schedule, EventBridge bus and rules as well as the IAM resources required for Scheduler to interact with EventBridge and CloudWatch.",
        "This pattern uses templated targets to interact with EventBridge directly."
      ]
    },
    "gitHub": {
      "template": {
        "repoURL": "https://github.com/aws-samples/serverless-patterns/tree/main/eventbridge-schedule-to-cloudwatch-terraform",
        "templateURL": "serverless-patterns/eventbridge-schedule-to-cloudwatch-terraform",
        "projectFolder": "eventbridge-schedule-to-cloudwatch-terraform",
        "templateFile": "eventbridge-schedule-to-cloudwatch-terraform/main.tf"
      }
    },
    "resources": {
      "bullets": [
        {
          "text": "Amazon EventBridge Scheduler",
          "link": "https://docs.aws.amazon.com/eventbridge/latest/userguide/scheduler.html"
        },
        {
          "text": "Send custom events to Amazon EventBridge",
          "link": "https://docs.aws.amazon.com/eventbridge/latest/APIReference/API_PutEvents.html"
        }
      ]
    },
    "deploy": {
      "text": [
        "terraform apply"
      ]
    },
    "testing": {
      "text": [
        "See the Github repo for detailed testing instructions."
      ]
    },
    "cleanup": {
      "text": [
        "Delete the stack: <code>terraform destroy</code>."
      ]
    },
    "authors": [
      {
        "name": "Ian Lodge",
        "image": "https://avatars.githubusercontent.com/u/135351711?v=4",
        "bio": "Ian is a Solutions Architect at Amazon Web Services based in the US.",
        "linkedin": "https://www.linkedin.com/in/ian-lodge"
      }
    ]
  }
  